CHANGELOG.txt
LICENSE.txt
MANIFEST.in
README.rst
VERSION
doc-requirements.txt
setup.cfg
setup.py
test-requirements.txt
docs/Makefile
docs/make.bat
docs/source/conf.py
docs/source/index.rst
docs/source/mock_missing.py
docs/source/pywin32.rst
docs/source/_templates/module_template.rst
pywin32_ctypes.egg-info/PKG-INFO
pywin32_ctypes.egg-info/SOURCES.txt
pywin32_ctypes.egg-info/dependency_links.txt
pywin32_ctypes.egg-info/not-zip-safe
pywin32_ctypes.egg-info/top_level.txt
win32ctypes/__init__.py
win32ctypes/pywintypes.py
win32ctypes/version.py
win32ctypes/win32api.py
win32ctypes/win32cred.py
win32ctypes/core/__init__.py
win32ctypes/core/_winerrors.py
win32ctypes/core/compat.py
win32ctypes/core/cffi/__init__.py
win32ctypes/core/cffi/_authentication.py
win32ctypes/core/cffi/_common.py
win32ctypes/core/cffi/_dll.py
win32ctypes/core/cffi/_nl_support.py
win32ctypes/core/cffi/_resource.py
win32ctypes/core/cffi/_system_information.py
win32ctypes/core/cffi/_time.py
win32ctypes/core/cffi/_util.py
win32ctypes/core/ctypes/__init__.py
win32ctypes/core/ctypes/_authentication.py
win32ctypes/core/ctypes/_common.py
win32ctypes/core/ctypes/_dll.py
win32ctypes/core/ctypes/_nl_support.py
win32ctypes/core/ctypes/_resource.py
win32ctypes/core/ctypes/_system_information.py
win32ctypes/core/ctypes/_time.py
win32ctypes/core/ctypes/_util.py
win32ctypes/pywin32/__init__.py
win32ctypes/pywin32/pywintypes.py
win32ctypes/pywin32/win32api.py
win32ctypes/pywin32/win32cred.py
win32ctypes/tests/__init__.py
win32ctypes/tests/test_backends.py
win32ctypes/tests/test_win32api.py
win32ctypes/tests/test_win32cred.py