Metadata-Version: 1.2
Name: pywin32-ctypes
Version: 0.2.2
Summary: A (partial) reimplementation of pywin32 using ctypes/cffi
Home-page: https://github.com/enthought/pywin32-ctypes
Author: Enthought Inc.
Author-email: info@enthough.com
License: BSD-3-Clause
Platform: UNKNOWN
Classifier: Programming Language :: Python :: 3
Classifier: Programming Language :: Python :: 3.6
Classifier: Programming Language :: Python :: 3.7
Classifier: Programming Language :: Python :: 3.8
Classifier: Programming Language :: Python :: 3.9
Classifier: Programming Language :: Python :: 3.10
Classifier: Programming Language :: Python :: 3.11
Requires-Python: >=3.6
